nexrpa/__init__.py
nexrpa/environment.py
nexrpa/nexutil.py
nexrpa/recorder.py
nexrpa/secrets.py
nexrpa-1.0.0.dist-info/LICENSE.txt
nexrpa-1.0.0.dist-info/METADATA
nexrpa-1.0.0.dist-info/WHEEL
nexrpa-1.0.0.dist-info/top_level.txt
nexrpa-1.0.0.dist-info/RECORD
