Metadata-Version: 2.1
Name: nexrpa
Version: 1.0.0
Summary: Nexrpa Python Automation Libraries
Author: Nishan (Nexrpa)
Author-email: <nexdigiai@gmail.com>
Keywords: python,video,stream,sockets
Classifier: Development Status :: 1 - Planning
Classifier: Intended Audience :: Developers
Classifier: Programming Language :: Python :: 3
Classifier: Operating System :: Unix
Classifier: Operating System :: MacOS :: MacOS X
Classifier: Operating System :: Microsoft :: Windows
License-File: LICENSE.txt
Requires-Dist: opencv-python
Requires-Dist: pyautogui
Requires-Dist: pyaudio
